eark_models/__init__.py
eark_models/etree.py
eark_models/langstring.py
eark_models/namespaces.py
eark_models/utils.py
eark_models/dc_schema/__init__.py
eark_models/dc_schema/v2_1.py
eark_models/mets/__init__.py
eark_models/mets/v1_12_1.py
eark_models/mods/__init__.py
eark_models/mods/v3_7.py
eark_models/premis/__init__.py
eark_models/premis/v3_0.py
eark_models/sip/__init__.py
eark_models/sip/v2_2_0.py
eark_models/xlink/__init__.py
eark_models/xlink/v2.py
sipin_eark_models-0.0.12.dist-info/licenses/LICENSE
sipin_eark_models-0.0.12.dist-info/METADATA
sipin_eark_models-0.0.12.dist-info/WHEEL
sipin_eark_models-0.0.12.dist-info/top_level.txt
sipin_eark_models-0.0.12.dist-info/RECORD
